{
  "type": "Feature",
  "properties": {
    "kingdom": "Cush",
    "era": "Napatan Period"
  },
  "geometry": {
    "type": "Polygon",
    "coordinates": [
      [
        [
          30.0,
          24.0
        ],
        [
          31.0,
          24.0
        ],
        [
          32.0,
          23.5
        ],
        [
          33.0,
          22.5
        ],
        [
          34.0,
          21.0
        ],
        [
          34.5,
          20.0
        ],
        [
          34.5,
          19.0
        ],
        [
          34.0,
          18.0
        ],
        [
          33.5,
          17.0
        ],
        [
          33.0,
          16.0
        ],
        [
          32.5,
          15.5
        ],
        [
          32.0,
          15.5
        ],
        [
          31.5,
          16.0
        ],
        [
          31.0,
          16.5
        ],
        [
          30.5,
          17.0
        ],
        [
          30.0,
          18.0
        ],
        [
          29.5,
          19.0
        ],
        [
          29.5,
          20.0
        ],
        [
          29.5,
          21.0
        ],
        [
          29.5,
          22.0
        ],
        [
          29.8,
          23.0
        ],
        [
          30.0,
          24.0
        ]
      ]
    ]
  }
}